[
  {
    "id": "vc-kiber",
    "title": "Kiberqáwipsizlik video kursı",
    "description": "Kiberqáwipsizlik negizleri — «Kiberqáwipsizlik» video darslar toplamınan 5 sabaq.",
    "icon": "video",
    "playlistUrl": "https://www.youtube.com/playlist?list=PLFRnhpV9odGDXUoUp5p50A6NHH4m4v7qS",
    "order": 1,
    "videos": [
      {
        "id": "vid-1",
        "youtubeId": "unTavenYgDo",
        "title": "Kiberqáwipsizlik nima?",
        "theme": "Kiberqáwipsizlikke kirisiw",
        "duration": "~45 mın",
        "description": "Kiberqáwipsizlik túsiniwi, maǵlıwmat qorǵawı hám zamanaǵı qáwipler haqqında kirisiw dars."
      },
      {
        "id": "vid-2",
        "youtubeId": "tAzT4h0Pwt0",
        "title": "CIA uchligi",
        "theme": "Kiberqáwipsizlikke kirisiw",
        "duration": "~40 mın",
        "description": "Confidentiality, Integrity, Availability — qorǵaw strategiyası negizi."
      },
      {
        "id": "vid-3",
        "youtubeId": "9Il1tlODnVA",
        "title": "Kiberhujumlar",
        "theme": "Qáwipler hám hujumlar",
        "duration": "~50 mın",
        "description": "Kiber hujum túrleri, qanday isleydi hám qarsı sharaalar."
      },
      {
        "id": "vid-4",
        "youtubeId": "AEHK_2RT30c",
        "title": "Firewall",
        "theme": "Tarmaq qáwipsizligi",
        "duration": "~35 mın",
        "description": "Firewall qanday isleydi, qoideler hám tarmoq qorǵawı."
      },
      {
        "id": "vid-5",
        "youtubeId": "UhSSY7HToZk",
        "title": "Maǵlıwmatlardı maxfiylashtiriw",
        "theme": "Kriptografiya",
        "duration": "~40 mın",
        "description": "Shifrlaw, maxfiylik hám maǵlıwmatlardı qorǵaw usılları."
      }
    ]
  }
]
